<?xml version="1.0" encoding="UTF-8"?>
<predicate uri="/fictional_universe/character_gender"><meta><reverse-query><cts:word-query xmlns:cts="http://marklogic.com/cts">
      <cts:text xml:lang="en">gender</cts:text>
      <cts:option>case-insensitive</cts:option>
      <cts:option>diacritic-insensitive</cts:option>
      <cts:option>punctuation-insensitive</cts:option>
      <cts:option>whitespace-insensitive</cts:option>
      <cts:option>stemmed</cts:option>
    </cts:word-query></reverse-query></meta><phrase>gender</phrase></predicate>